Workbook

Sheet Index
A1: Forensic Accounting Workpapers
A2: Template from the Bank Statement Analyzer · Justice for Fraud Victims Project · Apache 2.0
B4: Case name
B5: Client
B6: Engagement / matter no.
B7: Period examined
B8: Prepared by
B9: Reviewed by
A11: Ref | B11: Workpaper | C11: What it is for | D11: Prepared (initials / date) | E11: Reviewed (initials / date)
A12: A-1 | B12: Scope and questions | C12: List each question the client asked (from the engagement letter), in their words.
A13: A-2 | B13: Document index | C13: Every document received, when and from whom.
A14: B-1 | B14: Bank reconciliation (proof of each statement) | C14: Prove each statement before relying on it: beginning balance + deposits - withdrawals should equal the ending balance the bank printed.
A15: B-2 | B15: Sources and uses of funds | C15: One account per block (copy the block for each account).
A16: C-1 | B16: Fund tracing | C16: Follow each significant payment out of the victim's accounts to where it arrived.
A17: C-2 | B17: Payee analysis: paid versus supported | C17: One row per payee who matters to the case (the app's "New payee" findings are a good start).
A18: C-3 | B18: Cash analysis | C18: Every cash withdrawal (branch, ATM, cash advance).
A19: D-1 | B19: Red flag log | C19: Every red flag: the app's "Fraud patterns found" and Document Check warnings, and anything found by hand.
A20: D-2 | B20: Document authenticity | C20: One column per questioned document.
A21: E-1 | B21: Loss calculation | C21: Build the amount up from the workpapers, one line per component, and say what each rests on.
A22: F-1 | B22: Findings summary | C22: One row per question on A-1.
A23: R-1 | B23: Review notes | C23: The reviewer's questions and the preparer's answers.
A25: Key
B26: Blue cells: type here
B27: Shaded cells: formulas and totals (don't type over them)
A28: Example | B28: Gray italic row on each sheet: an example from the Hartwell case. Delete it before you start.
A30: Tickmarks
A31: A | B31: Agreed to the source document (statement, check image, wire record)
A32: F | B32: Footed: the column adds to the total shown
A33: R | B33: Recomputed: the calculation was redone and agrees
A34: T | B34: Traced to the receiving account
A35: N | B35: No exception noted
A36: X | B36: Exception: see the note

Sheet A-1
A1: =IF(Index!$C$4="","[Case name: fill in on the Index]",Index!$C$4) | E1: Prepared by / date
A2: A-1 Scope and questions | E2: Reviewed by / date
A4: List each question the client asked (from the engagement letter), in their words. For each, name the workpapers that answer it and track its status. Note any limits on the work: missing records, documents you could not verify.
A8: # | B8: Question asked by the client | C8: Answered in (WP refs) | D8: Status | E8: Limitations / records still needed | F8: Notes
A9: 1 | B9: What money left Mrs. Hartwell's accounts from 3/1 to 5/31/2025, and where did it go? | C9: B-2, C-1, C-3 | D9: Open | E9: Casino ATM cash can't be traced from bank records

Sheet A-2
A1: =IF(Index!$C$4="","[Case name: fill in on the Index]",Index!$C$4) | J1: Prepared by / date
A2: A-2 Document index | J2: Reviewed by / date
A4: Every document received, when and from whom. Copy each statement's SHA-256 fingerprint from the app's Evidence record (Download Workpapers tab, or the Evidence sheet of the app's workpaper) so anyone can later confirm it is the same file. Record the Document Check result for each statement.
A8: Doc ID | B8: Description | C8: Source (who produced it) | D8: How obtained | E8: Date received | F8: File name | G8: SHA-256 (from the app) | H8: Pages | I8: Period covered | J8: Document Check result | K8: Notes
A9: 5 | B9: April 2025 checking statement, "family copy" | C9: Dana Pruitt (by email) | D9: Client | E9: 45832 | F9: 5_checking_2025-04_family_copy.pdf | G9: (copy from the app) | H9: 1 | I9: 04/01-04/30/2025 | J9: May have been altered | K9: Compare with Doc 2, the bank's copy

Sheet B-1
A1: =IF(Index!$C$4="","[Case name: fill in on the Index]",Index!$C$4) | L1: Prepared by / date
A2: B-1 Bank reconciliation (proof of each statement) | L2: Reviewed by / date
A4: Prove each statement before relying on it: beginning balance + deposits - withdrawals should equal the ending balance the bank printed. Deposits and withdrawals come from the transactions the app read (Transactions tab, or the workpaper). A difference means a missed or misread line, or an altered statement. Record the app's Bank Reconciliation result too.
A8: Doc ID | B8: Bank | C8: Account (last 4) | D8: Period | E8: Beginning balance (per statement) | F8: Deposits (per detail) | G8: Withdrawals (per detail) | H8: Computed ending | I8: Ending balance (per statement) | J8: Difference | K8: Result | L8: App's result | M8: Tickmarks / notes
A9: 2 | B9: Larkspur Valley Bank | C9: 8701 | D9: 04/01-04/30/2025 | E9: 16760.41 | F9: 52970.67 | G9: 50647.92 | H9: =IF(E9="","",E9+F9-G9) | I9: 19083.16 | J9: =IF(OR(H9="",I9=""),"",ROUND(I9-H9,2)) | K9: =IF(J9="","",IF(ABS(J9)<0.005,"Reconciled","Variance")) | L9: Reconciled | M9: A F R
H10: =IF(E10="","",E10+F10-G10) | J10: =IF(OR(H10="",I10=""),"",ROUND(I10-H10,2)) | K10: =IF(J10="","",IF(ABS(J10)<0.005,"Reconciled","Variance"))
H11: =IF(E11="","",E11+F11-G11) | J11: =IF(OR(H11="",I11=""),"",ROUND(I11-H11,2)) | K11: =IF(J11="","",IF(ABS(J11)<0.005,"Reconciled","Variance"))
H12: =IF(E12="","",E12+F12-G12) | J12: =IF(OR(H12="",I12=""),"",ROUND(I12-H12,2)) | K12: =IF(J12="","",IF(ABS(J12)<0.005,"Reconciled","Variance"))
H13: =IF(E13="","",E13+F13-G13) | J13: =IF(OR(H13="",I13=""),"",ROUND(I13-H13,2)) | K13: =IF(J13="","",IF(ABS(J13)<0.005,"Reconciled","Variance"))
H14: =IF(E14="","",E14+F14-G14) | J14: =IF(OR(H14="",I14=""),"",ROUND(I14-H14,2)) | K14: =IF(J14="","",IF(ABS(J14)<0.005,"Reconciled","Variance"))
H15: =IF(E15="","",E15+F15-G15) | J15: =IF(OR(H15="",I15=""),"",ROUND(I15-H15,2)) | K15: =IF(J15="","",IF(ABS(J15)<0.005,"Reconciled","Variance"))
H16: =IF(E16="","",E16+F16-G16) | J16: =IF(OR(H16="",I16=""),"",ROUND(I16-H16,2)) | K16: =IF(J16="","",IF(ABS(J16)<0.005,"Reconciled","Variance"))
H17: =IF(E17="","",E17+F17-G17) | J17: =IF(OR(H17="",I17=""),"",ROUND(I17-H17,2)) | K17: =IF(J17="","",IF(ABS(J17)<0.005,"Reconciled","Variance"))
H18: =IF(E18="","",E18+F18-G18) | J18: =IF(OR(H18="",I18=""),"",ROUND(I18-H18,2)) | K18: =IF(J18="","",IF(ABS(J18)<0.005,"Reconciled","Variance"))
H19: =IF(E19="","",E19+F19-G19) | J19: =IF(OR(H19="",I19=""),"",ROUND(I19-H19,2)) | K19: =IF(J19="","",IF(ABS(J19)<0.005,"Reconciled","Variance"))
H20: =IF(E20="","",E20+F20-G20) | J20: =IF(OR(H20="",I20=""),"",ROUND(I20-H20,2)) | K20: =IF(J20="","",IF(ABS(J20)<0.005,"Reconciled","Variance"))
H21: =IF(E21="","",E21+F21-G21) | J21: =IF(OR(H21="",I21=""),"",ROUND(I21-H21,2)) | K21: =IF(J21="","",IF(ABS(J21)<0.005,"Reconciled","Variance"))
... H39: =IF(E39="","",E39+F39-G39) | J39: =IF(OR(H39="",I39=""),"",ROUND(I39-H39,2)) | K39: =IF(J39="","",IF(ABS(J39)<0.005,"Reconciled","Variance"))
A40: Total | F40: =SUM(F9:F39) | G40: =SUM(G9:G39)

Sheet B-2
A1: =IF(Index!$C$4="","[Case name: fill in on the Index]",Index!$C$4) | E1: Prepared by / date
A2: B-2 Sources and uses of funds | E2: Reviewed by / date
A4: One account per block (copy the block for each account). Rename the categories to fit the case. Sources are money in; uses are money out, grouped so the unusual stands out (payments to the subject, cash, gambling). The check row should be zero: if it isn't, a transaction is missing or double-counted.
A8: Account: ________________ | B8: Month 1 | C8: Month 2 | D8: Month 3 | E8: Total | F8: Notes
A9: Opening balance | C9: =IF(B26="",B25,B26) | D9: =IF(C26="",C25,C26) | E9: =B9
A10: Sources
A11: Pension | E11: =SUM(B11:D11)
A12: Social Security | E12: =SUM(B12:D12)
A13: CD maturity / transfers from savings | E13: =SUM(B13:D13)
A14: Other deposits | E14: =SUM(B14:D14)
A15: Total sources | B15: =SUM(B11:B14) | C15: =SUM(C11:C14) | D15: =SUM(D11:D14) | E15: =SUM(B15:D15)
A16: Uses
A17: Ordinary living expenses (utilities, groceries, insurance) | E17: =SUM(B17:D17)
A18: Payments to the subject or related parties | E18: =SUM(B18:D18)
A19: Cash withdrawals (branch and ATM) | E19: =SUM(B19:D19)
A20: Gambling | E20: =SUM(B20:D20)
A21: Gift cards | E21: =SUM(B21:D21)
A22: Fees (overdraft, wire, ATM) | E22: =SUM(B22:D22)
A23: Other | E23: =SUM(B23:D23)
A24: Total uses | B24: =SUM(B17:B23) | C24: =SUM(C17:C23) | D24: =SUM(D17:D23) | E24: =SUM(B24:D24)
A25: Computed ending balance | B25: =B9+B15-B24 | C25: =C9+C15-C24 | D25: =D9+D15-D24 | E25: =D25
A26: Ending balance per statement | E26: =D26
A27: Check (should be 0) | B27: =ROUND(B26-B25,2) | C27: =ROUND(C26-C25,2) | D27: =ROUND(D26-D25,2) | E27: =ROUND(E26-E25,2)

Sheet C-1
A1: =IF(Index!$C$4="","[Case name: fill in on the Index]",Index!$C$4) | N1: Prepared by / date
A2: C-1 Fund tracing | N2: Reviewed by / date
A4: Follow each significant payment out of the victim's accounts to where it arrived. One row per payment. Match by amount, date (usually 0 to 3 business days later) and reference: check endorsements, wire beneficiary details, Zelle confirmation numbers. Traced = found arriving in a named account. The summary below the table totals what was traced by method.
A8: Trace # | B8: Date out | C8: From (bank / account) | D8: Description on statement | E8: Amount out | F8: Method | G8: Recipient | H8: Receiving bank / account | I8: Date in | J8: Amount in | K8: Difference | L8: Days | M8: Traced? | N8: Evidence (doc / WP ref) | O8: Notes
A9: 1 | B9: 45762 | C9: Larkspur 8701 | D9: WIRE TRANSFER OUT DP COMPANION CARE LLC REF 88213 | E9: 24000 | F9: Wire | G9: DP Companion Care LLC | H9: Quillbrook CU 70033390 | I9: 45762 | J9: 24000 | K9: =IF(OR(E9="",J9=""),"",ROUND(J9-E9,2)) | L9: =IF(OR(B9="",I9=""),"",I9-B9) | M9: Yes | N9: Docs 2, 7; Exhibit G | O9: $18,750 left next day as check 1001 (SUV)
K10: =IF(OR(E10="",J10=""),"",ROUND(J10-E10,2)) | L10: =IF(OR(B10="",I10=""),"",I10-B10)
K11: =IF(OR(E11="",J11=""),"",ROUND(J11-E11,2)) | L11: =IF(OR(B11="",I11=""),"",I11-B11)
K12: =IF(OR(E12="",J12=""),"",ROUND(J12-E12,2)) | L12: =IF(OR(B12="",I12=""),"",I12-B12)
K13: =IF(OR(E13="",J13=""),"",ROUND(J13-E13,2)) | L13: =IF(OR(B13="",I13=""),"",I13-B13)
K14: =IF(OR(E14="",J14=""),"",ROUND(J14-E14,2)) | L14: =IF(OR(B14="",I14=""),"",I14-B14)
K15: =IF(OR(E15="",J15=""),"",ROUND(J15-E15,2)) | L15: =IF(OR(B15="",I15=""),"",I15-B15)
K16: =IF(OR(E16="",J16=""),"",ROUND(J16-E16,2)) | L16: =IF(OR(B16="",I16=""),"",I16-B16)
K17: =IF(OR(E17="",J17=""),"",ROUND(J17-E17,2)) | L17: =IF(OR(B17="",I17=""),"",I17-B17)
K18: =IF(OR(E18="",J18=""),"",ROUND(J18-E18,2)) | L18: =IF(OR(B18="",I18=""),"",I18-B18)
K19: =IF(OR(E19="",J19=""),"",ROUND(J19-E19,2)) | L19: =IF(OR(B19="",I19=""),"",I19-B19)
K20: =IF(OR(E20="",J20=""),"",ROUND(J20-E20,2)) | L20: =IF(OR(B20="",I20=""),"",I20-B20)
K21: =IF(OR(E21="",J21=""),"",ROUND(J21-E21,2)) | L21: =IF(OR(B21="",I21=""),"",I21-B21)
... K39: =IF(OR(E39="",J39=""),"",ROUND(J39-E39,2)) | L39: =IF(OR(B39="",I39=""),"",I39-B39)
A40: Total | E40: =SUM(E9:E39) | J40: =SUM(J9:J39)
D42: Summary by method | E42: Amount out | F42: Traced (Yes)
D43: Check | E43: =SUMIFS($E$9:$E$39,$F$9:$F$39,D43) | F43: =SUMIFS($J$9:$J$39,$F$9:$F$39,D43,$M$9:$M$39,"Yes")
D44: Wire | E44: =SUMIFS($E$9:$E$39,$F$9:$F$39,D44) | F44: =SUMIFS($J$9:$J$39,$F$9:$F$39,D44,$M$9:$M$39,"Yes")
D45: Zelle / ACH | E45: =SUMIFS($E$9:$E$39,$F$9:$F$39,D45) | F45: =SUMIFS($J$9:$J$39,$F$9:$F$39,D45,$M$9:$M$39,"Yes")
D46: Online transfer | E46: =SUMIFS($E$9:$E$39,$F$9:$F$39,D46) | F46: =SUMIFS($J$9:$J$39,$F$9:$F$39,D46,$M$9:$M$39,"Yes")
D47: Cash | E47: =SUMIFS($E$9:$E$39,$F$9:$F$39,D47) | F47: =SUMIFS($J$9:$J$39,$F$9:$F$39,D47,$M$9:$M$39,"Yes")
D48: Debit card | E48: =SUMIFS($E$9:$E$39,$F$9:$F$39,D48) | F48: =SUMIFS($J$9:$J$39,$F$9:$F$39,D48,$M$9:$M$39,"Yes")
D49: Credit card | E49: =SUMIFS($E$9:$E$39,$F$9:$F$39,D49) | F49: =SUMIFS($J$9:$J$39,$F$9:$F$39,D49,$M$9:$M$39,"Yes")
D50: Other | E50: =SUMIFS($E$9:$E$39,$F$9:$F$39,D50) | F50: =SUMIFS($J$9:$J$39,$F$9:$F$39,D50,$M$9:$M$39,"Yes")

Sheet C-2
A1: =IF(Index!$C$4="","[Case name: fill in on the Index]",Index!$C$4) | J1: Prepared by / date
A2: C-2 Payee analysis: paid versus supported | J2: Reviewed by / date
A4: One row per payee who matters to the case (the app's "New payee" findings are a good start). Supported = what an agreement, invoice or other document justifies. The calculator below works out the most a caregiver could have earned under an hourly agreement.
A8: Payee | B8: Related to the subject? | C8: First paid | D8: Last paid | E8: Number of payments | F8: Total paid | G8: Support (document) | H8: Supported amount | I8: Unsupported | J8: WP / doc ref | K8: Notes
A9: DP Companion Care LLC | B9: Yes | C9: 45755 | D9: 45786 | E9: 5 | F9: 29400 | G9: Invoice INV-1001 (Exhibit D) | H9: 576 | I9: =IF(F9="","",F9-N(H9)) | J9: C-1, Exhibits C, D | K9: Agreement: $24/hr, 12 hrs/week
I10: =IF(F10="","",F10-N(H10))
I11: =IF(F11="","",F11-N(H11))
I12: =IF(F12="","",F12-N(H12))
I13: =IF(F13="","",F13-N(H13))
I14: =IF(F14="","",F14-N(H14))
I15: =IF(F15="","",F15-N(H15))
I16: =IF(F16="","",F16-N(H16))
I17: =IF(F17="","",F17-N(H17))
I18: =IF(F18="","",F18-N(H18))
I19: =IF(F19="","",F19-N(H19))
I20: =IF(F20="","",F20-N(H20))
I21: =IF(F21="","",F21-N(H21))
... I24: =IF(F24="","",F24-N(H24))
A25: Total | E25: =SUM(E9:E24) | F25: =SUM(F9:F24) | H25: =SUM(H9:H24) | I25: =SUM(I9:I24)
A27: Most that could be earned under an hourly agreement
A28: Hourly rate
A29: Hours per week
A30: Weeks in the period
A31: Maximum earned | B31: =N(B28)*N(B29)*N(B30)

Sheet C-3
A1: =IF(Index!$C$4="","[Case name: fill in on the Index]",Index!$C$4) | L1: Prepared by / date
A2: C-3 Cash analysis | L2: Reviewed by / date
A4: Every cash withdrawal (branch, ATM, cash advance). The sheet marks amounts from $8,000 to $9,999.99 (just under the $10,000 reporting threshold) and the days since the previous withdrawal. Then look for matching cash deposits in the subject's accounts, a few days later and a little less.
A8: Date | B8: Account | C8: Where (branch / ATM / casino) | D8: Amount | E8: Just under $10,000? | F8: Days since previous | G8: Matching deposit: date | H8: Deposit account | I8: Deposit amount | J8: Days later | K8: Kept by subject? | L8: Evidence | M8: Notes
A9: 45768 | B9: Larkspur 8701 | C9: 1st Ave branch, Maple Grove | D9: 9500 | E9: =IF(D9="","",IF(AND(D9>=8000,D9<10000),"Yes","No")) | G9: 45769 | H9: Oxbow 5520 | I9: 9000 | J9: =IF(OR(A9="",G9=""),"",G9-A9) | K9: Yes | L9: Docs 2, 9 | M9: Deposit $500 less, next day
E10: =IF(D10="","",IF(AND(D10>=8000,D10<10000),"Yes","No")) | F10: =IF(OR(A10="",N(A9)=0),"",A10-A9) | J10: =IF(OR(A10="",G10=""),"",G10-A10)
E11: =IF(D11="","",IF(AND(D11>=8000,D11<10000),"Yes","No")) | F11: =IF(OR(A11="",N(A10)=0),"",A11-A10) | J11: =IF(OR(A11="",G11=""),"",G11-A11)
E12: =IF(D12="","",IF(AND(D12>=8000,D12<10000),"Yes","No")) | F12: =IF(OR(A12="",N(A11)=0),"",A12-A11) | J12: =IF(OR(A12="",G12=""),"",G12-A12)
E13: =IF(D13="","",IF(AND(D13>=8000,D13<10000),"Yes","No")) | F13: =IF(OR(A13="",N(A12)=0),"",A13-A12) | J13: =IF(OR(A13="",G13=""),"",G13-A13)
E14: =IF(D14="","",IF(AND(D14>=8000,D14<10000),"Yes","No")) | F14: =IF(OR(A14="",N(A13)=0),"",A14-A13) | J14: =IF(OR(A14="",G14=""),"",G14-A14)
E15: =IF(D15="","",IF(AND(D15>=8000,D15<10000),"Yes","No")) | F15: =IF(OR(A15="",N(A14)=0),"",A15-A14) | J15: =IF(OR(A15="",G15=""),"",G15-A15)
E16: =IF(D16="","",IF(AND(D16>=8000,D16<10000),"Yes","No")) | F16: =IF(OR(A16="",N(A15)=0),"",A16-A15) | J16: =IF(OR(A16="",G16=""),"",G16-A16)
E17: =IF(D17="","",IF(AND(D17>=8000,D17<10000),"Yes","No")) | F17: =IF(OR(A17="",N(A16)=0),"",A17-A16) | J17: =IF(OR(A17="",G17=""),"",G17-A17)
E18: =IF(D18="","",IF(AND(D18>=8000,D18<10000),"Yes","No")) | F18: =IF(OR(A18="",N(A17)=0),"",A18-A17) | J18: =IF(OR(A18="",G18=""),"",G18-A18)
E19: =IF(D19="","",IF(AND(D19>=8000,D19<10000),"Yes","No")) | F19: =IF(OR(A19="",N(A18)=0),"",A19-A18) | J19: =IF(OR(A19="",G19=""),"",G19-A19)
E20: =IF(D20="","",IF(AND(D20>=8000,D20<10000),"Yes","No")) | F20: =IF(OR(A20="",N(A19)=0),"",A20-A19) | J20: =IF(OR(A20="",G20=""),"",G20-A20)
E21: =IF(D21="","",IF(AND(D21>=8000,D21<10000),"Yes","No")) | F21: =IF(OR(A21="",N(A20)=0),"",A21-A20) | J21: =IF(OR(A21="",G21=""),"",G21-A21)
... E39: =IF(D39="","",IF(AND(D39>=8000,D39<10000),"Yes","No")) | F39: =IF(OR(A39="",N(A38)=0),"",A39-A38) | J39: =IF(OR(A39="",G39=""),"",G39-A39)
A40: Total | D40: =SUM(D9:D39) | I40: =SUM(I9:I39)
A42: Total cash out | B42: =SUM(D9:D39)
A43: Withdrawals just under $10,000 | B43: =COUNTIF(E9:E39,"Yes")
A44: Matched to subject's deposits | B44: =SUM(I9:I39)
A45: Share of cash matched | B45: =IF(N(B42)=0,"",B44/B42)

Sheet D-1
A1: =IF(Index!$C$4="","[Case name: fill in on the Index]",Index!$C$4) | J1: Prepared by / date
A2: D-1 Red flag log | J2: Reviewed by / date
A4: Every red flag: the app's "Fraud patterns found" and Document Check warnings, and anything found by hand. A flag is a lead, not a conclusion. Record what was done to follow it up and whether it was explained.
A8: # | B8: Red flag | C8: Source (app / manual) | D8: Account | E8: Date(s) | F8: Amount | G8: Risk | H8: Follow-up performed | I8: Result / explanation | J8: Status | K8: WP ref
A9: 1 | B9: Cash withdrawals kept just under $10,000 | C9: App | D9: Larkspur 8701 | E9: 04/21-05/23/2025 | F9: 33380 | G9: High | H9: Searched subject's statements for cash deposits | I9: $31,800 deposited by Dana 1-4 days later | J9: Resolved: unexplained | K9: C-3
A40: Total | F40: =SUM(F9:F39)

Sheet D-2
A1: =IF(Index!$C$4="","[Case name: fill in on the Index]",Index!$C$4) | E1: Prepared by / date
A2: D-2 Document authenticity | E2: Reviewed by / date
A4: One column per questioned document. Fill in the app's Document Check result for each check, then the checks only a person can do. A warning is a reason to get the statement directly from the bank; a clean result doesn't prove a document is genuine.
A8: Check | B8: Document 1: | C8: Document 2: | D8: Document 3: | E8: Document 4: | F8: Notes
A9: Software that made the PDF
A10: Saved again after it was created
A11: Fonts on transaction lines
A12: Page numbers match the file
A13: Dates inside the statement period
A14: Transactions in date order
A15: Descriptions match money in and out
A16: Running balances add up
A17: Summary agrees with the transactions
A18: Amounts formatted consistently
A19: Text left by an AI tool
A20: Dates that exist
... A29: Conclusion for each document

Sheet E-1
A1: =IF(Index!$C$4="","[Case name: fill in on the Index]",Index!$C$4) | F1: Prepared by / date
A2: E-1 Loss calculation | F2: Reviewed by / date
A4: Build the amount up from the workpapers, one line per component, and say what each rests on. Only lines marked Include = Yes count in the total; the summary splits the total by basis so the reader sees what is traced and what is only unexplained.
A8: Component | B8: Amount | C8: Basis | D8: Include? | E8: WP ref | F8: Calculation / support | G8: Notes
A9: Payments to DP Companion Care LLC and Dana Pruitt, less invoiced care | B9: 33824 | C9: Unsupported payment | D9: Yes | E9: C-1, C-2 | F9: $34,400 paid - $576 invoiced
A26: Total included | B26: =SUMIFS(B9:B24,D9:D24,"Yes")
A27: of which: Traced to subject | B27: =SUMIFS(B9:B24,D9:D24,"Yes",C9:C24,"Traced to subject")
A28: of which: Unsupported payment | B28: =SUMIFS(B9:B24,D9:D24,"Yes",C9:C24,"Unsupported payment")
A29: of which: Unexplained | B29: =SUMIFS(B9:B24,D9:D24,"Yes",C9:C24,"Unexplained")
A30: of which: Supported (exclude) | B30: =SUMIFS(B9:B24,D9:D24,"Yes",C9:C24,"Supported (exclude)")

Sheet F-1
A1: =IF(Index!$C$4="","[Case name: fill in on the Index]",Index!$C$4) | E1: Prepared by / date
A2: F-1 Findings summary | E2: Reviewed by / date
A4: One row per question on A-1. State what the records show, the amount, and the workpapers behind it. Write findings as "consistent with" or "not consistent with" the explanations offered; leave intent and guilt to the court. Say what you could not determine and what record would settle it.
A8: # | B8: Question (from A-1) | C8: Finding | D8: Amount | E8: Support (WP refs) | F8: Limitations / not determined
A9: 4 | B9: Does the Wrenfield statement show the $24,000 was repaid? | C9: The statement has four signs of an AI-generated document, and the repayments it shows do not appear in Mrs. Hartwell's May statement. Not consistent with repayment. | D9: 24000 | E9: A-2, D-2 | F9: Wrenfield Trust Bank not contacted

Sheet R-1
A1: =IF(Index!$C$4="","[Case name: fill in on the Index]",Index!$C$4) | F1: Prepared by / date
A2: R-1 Review notes | F2: Reviewed by / date
A4: The reviewer's questions and the preparer's answers. Every note is cleared before the file is final.
A8: # | B8: WP ref | C8: Reviewer's note | D8: Preparer's response | E8: Cleared by | F8: Date | G8: Open?
